[
  {
    "chars": 160,
    "audio_chunks": 333,
    "audio_bytes": 878592,
    "alignment_total_reported_chars": 159,
    "alignment_stream_chars": 159,
    "alignment_unique_indices": 159,
    "alignment_matched_chars": 159,
    "alignment_skipped_chars": 0,
    "alignment_missing_chars": 1,
    "alignment_coverage": 0.99375,
    "alignment_non_monotonic_count": 0,
    "alignment_non_positive_duration_count": 0,
    "alignment_tail_error_ms": -151.63265306122412,
    "alignment_abs_tail_error_ms": 151.63265306122412,
    "receiver_timed_out": false,
    "client_ttft_recv_ms": 146.7012920184061,
    "client_ttfb_msg_ms": 146.68012503534555,
    "client_total_audio_ms": 1086.9226249633357,
    "client_chars_per_s": 147.2045905801226,
    "run": 1,
    "run_id": "len-160-case-plain_01-run-1-b9ad6de7",
    "case": "plain_01",
    "server_session": "82bfe952",
    "server_ttft_audio_out_ms": 143.368,
    "server_ttft_send_ms": 145.59,
    "server_gap_buffer_to_synth_ms": 10.738,
    "server_gap_synth_to_first_chunk_ms": null,
    "server_gap_synth_to_backend_done_ms": 54.588,
    "server_gap_first_chunk_to_audio_out_ms": null,
    "server_gap_backend_done_to_audio_out_ms": 78.042,
    "server_gap_aligner_ms": 77.483,
    "server_gap_aligner_done_to_audio_out_ms": 0.039,
    "server_gap_math_normalize_ms": 0.014,
    "server_gap_audio_out_to_send_ms": 2.222,
    "server_model_compute_ms": 54.588,
    "server_post_model_to_audio_out_ms": 78.042,
    "client_minus_server_send_ms": NaN
  },
  {
    "chars": 160,
    "audio_chunks": 302,
    "audio_bytes": 796672,
    "alignment_total_reported_chars": 159,
    "alignment_stream_chars": 159,
    "alignment_unique_indices": 159,
    "alignment_matched_chars": 159,
    "alignment_skipped_chars": 0,
    "alignment_missing_chars": 1,
    "alignment_coverage": 0.99375,
    "alignment_non_monotonic_count": 0,
    "alignment_non_positive_duration_count": 0,
    "alignment_tail_error_ms": -82.15419501133874,
    "alignment_abs_tail_error_ms": 82.15419501133874,
    "receiver_timed_out": false,
    "client_ttft_recv_ms": 138.05899990256876,
    "client_ttfb_msg_ms": 138.0349169485271,
    "client_total_audio_ms": 1162.3704999219626,
    "client_chars_per_s": 137.64974249668398,
    "run": 1,
    "run_id": "len-160-case-plain_02-run-1-6b0ddf71",
    "case": "plain_02",
    "server_session": "c5a547a4",
    "server_ttft_audio_out_ms": 135.738,
    "server_ttft_send_ms": 137.408,
    "server_gap_buffer_to_synth_ms": 11.254,
    "server_gap_synth_to_first_chunk_ms": null,
    "server_gap_synth_to_backend_done_ms": 46.573,
    "server_gap_first_chunk_to_audio_out_ms": null,
    "server_gap_backend_done_to_audio_out_ms": 77.911,
    "server_gap_aligner_ms": 77.415,
    "server_gap_aligner_done_to_audio_out_ms": 0.04,
    "server_gap_math_normalize_ms": 0.015,
    "server_gap_audio_out_to_send_ms": 1.67,
    "server_model_compute_ms": 46.573,
    "server_post_model_to_audio_out_ms": 77.911,
    "client_minus_server_send_ms": NaN
  },
  {
    "chars": 160,
    "audio_chunks": 311,
    "audio_bytes": 820224,
    "alignment_total_reported_chars": 158,
    "alignment_stream_chars": 158,
    "alignment_unique_indices": 158,
    "alignment_matched_chars": 158,
    "alignment_skipped_chars": 0,
    "alignment_missing_chars": 2,
    "alignment_coverage": 0.9875,
    "alignment_non_monotonic_count": 0,
    "alignment_non_positive_duration_count": 0,
    "alignment_tail_error_ms": -183.67346938775518,
    "alignment_abs_tail_error_ms": 183.67346938775518,
    "receiver_timed_out": false,
    "client_ttft_recv_ms": 135.43212495278567,
    "client_ttfb_msg_ms": 135.40920894593,
    "client_total_audio_ms": 963.9960000058636,
    "client_chars_per_s": 165.9757924296644,
    "run": 1,
    "run_id": "len-160-case-plain_03-run-1-8095a41b",
    "case": "plain_03",
    "server_session": "02665670",
    "server_ttft_audio_out_ms": 132.934,
    "server_ttft_send_ms": 134.718,
    "server_gap_buffer_to_synth_ms": 11.616,
    "server_gap_synth_to_first_chunk_ms": null,
    "server_gap_synth_to_backend_done_ms": 43.614,
    "server_gap_first_chunk_to_audio_out_ms": null,
    "server_gap_backend_done_to_audio_out_ms": 77.705,
    "server_gap_aligner_ms": 77.205,
    "server_gap_aligner_done_to_audio_out_ms": 0.045,
    "server_gap_math_normalize_ms": 0.016,
    "server_gap_audio_out_to_send_ms": 1.784,
    "server_model_compute_ms": 43.614,
    "server_post_model_to_audio_out_ms": 77.705,
    "client_minus_server_send_ms": NaN
  },
  {
    "chars": 160,
    "audio_chunks": 331,
    "audio_bytes": 872448,
    "alignment_total_reported_chars": 158,
    "alignment_stream_chars": 158,
    "alignment_unique_indices": 158,
    "alignment_matched_chars": 158,
    "alignment_skipped_chars": 0,
    "alignment_missing_chars": 2,
    "alignment_coverage": 0.9875,
    "alignment_non_monotonic_count": 0,
    "alignment_non_positive_duration_count": 0,
    "alignment_tail_error_ms": -275.53287981859467,
    "alignment_abs_tail_error_ms": 275.53287981859467,
    "receiver_timed_out": false,
    "client_ttft_recv_ms": 147.322665899992,
    "client_ttfb_msg_ms": 147.29362493380904,
    "client_total_audio_ms": 1098.7884579226375,
    "client_chars_per_s": 145.61492600904728,
    "run": 1,
    "run_id": "len-160-case-plain_04-run-1-9a1fd56a",
    "case": "plain_04",
    "server_session": "28000217",
    "server_ttft_audio_out_ms": 144.871,
    "server_ttft_send_ms": 146.641,
    "server_gap_buffer_to_synth_ms": 11.138,
    "server_gap_synth_to_first_chunk_ms": null,
    "server_gap_synth_to_backend_done_ms": 55.836,
    "server_gap_first_chunk_to_audio_out_ms": null,
    "server_gap_backend_done_to_audio_out_ms": 77.897,
    "server_gap_aligner_ms": 77.286,
    "server_gap_aligner_done_to_audio_out_ms": 0.042,
    "server_gap_math_normalize_ms": 0.014,
    "server_gap_audio_out_to_send_ms": 1.77,
    "server_model_compute_ms": 55.836,
    "server_post_model_to_audio_out_ms": 77.897,
    "client_minus_server_send_ms": NaN
  },
  {
    "chars": 160,
    "audio_chunks": 327,
    "audio_bytes": 863232,
    "alignment_total_reported_chars": 160,
    "alignment_stream_chars": 160,
    "alignment_unique_indices": 160,
    "alignment_matched_chars": 160,
    "alignment_skipped_chars": 0,
    "alignment_missing_chars": 0,
    "alignment_coverage": 1.0,
    "alignment_non_monotonic_count": 0,
    "alignment_non_positive_duration_count": 0,
    "alignment_tail_error_ms": -203.92290249433245,
    "alignment_abs_tail_error_ms": 203.92290249433245,
    "receiver_timed_out": false,
    "client_ttft_recv_ms": 149.43312504328787,
    "client_ttfb_msg_ms": 149.40670900978148,
    "client_total_audio_ms": 1100.580041995272,
    "client_chars_per_s": 145.377886109884,
    "run": 1,
    "run_id": "len-160-case-plain_05-run-1-60c21c32",
    "case": "plain_05",
    "server_session": "434624de",
    "server_ttft_audio_out_ms": 146.362,
    "server_ttft_send_ms": 148.296,
    "server_gap_buffer_to_synth_ms": 11.136,
    "server_gap_synth_to_first_chunk_ms": null,
    "server_gap_synth_to_backend_done_ms": 53.226,
    "server_gap_first_chunk_to_audio_out_ms": null,
    "server_gap_backend_done_to_audio_out_ms": 82.0,
    "server_gap_aligner_ms": 81.485,
    "server_gap_aligner_done_to_audio_out_ms": 0.045,
    "server_gap_math_normalize_ms": 0.013,
    "server_gap_audio_out_to_send_ms": 1.934,
    "server_model_compute_ms": 53.226,
    "server_post_model_to_audio_out_ms": 82.0,
    "client_minus_server_send_ms": NaN
  },
  {
    "chars": 160,
    "audio_chunks": 401,
    "audio_bytes": 1058816,
    "alignment_total_reported_chars": 164,
    "alignment_stream_chars": 164,
    "alignment_unique_indices": 122,
    "alignment_matched_chars": 122,
    "alignment_skipped_chars": 42,
    "alignment_missing_chars": 38,
    "alignment_coverage": 0.7625,
    "alignment_non_monotonic_count": 0,
    "alignment_non_positive_duration_count": 0,
    "alignment_tail_error_ms": -478.1179138321986,
    "alignment_abs_tail_error_ms": 478.1179138321986,
    "receiver_timed_out": false,
    "client_ttft_recv_ms": 122.38279194571078,
    "client_ttfb_msg_ms": 122.35816696193069,
    "client_total_audio_ms": 1366.1419169511646,
    "client_chars_per_s": 117.1181397881956,
    "run": 1,
    "run_id": "len-160-case-math_01-run-1-43619565",
    "case": "math_01",
    "server_session": "863a019c",
    "server_ttft_audio_out_ms": 119.717,
    "server_ttft_send_ms": 121.347,
    "server_gap_buffer_to_synth_ms": 10.824,
    "server_gap_synth_to_first_chunk_ms": null,
    "server_gap_synth_to_backend_done_ms": 36.703,
    "server_gap_first_chunk_to_audio_out_ms": null,
    "server_gap_backend_done_to_audio_out_ms": 72.19,
    "server_gap_aligner_ms": 71.741,
    "server_gap_aligner_done_to_audio_out_ms": 0.038,
    "server_gap_math_normalize_ms": 0.022,
    "server_gap_audio_out_to_send_ms": 1.63,
    "server_model_compute_ms": 36.703,
    "server_post_model_to_audio_out_ms": 72.19,
    "client_minus_server_send_ms": NaN
  },
  {
    "chars": 160,
    "audio_chunks": 404,
    "audio_bytes": 1067008,
    "alignment_total_reported_chars": 202,
    "alignment_stream_chars": 202,
    "alignment_unique_indices": 122,
    "alignment_matched_chars": 134,
    "alignment_skipped_chars": 68,
    "alignment_missing_chars": 26,
    "alignment_coverage": 0.8375,
    "alignment_non_monotonic_count": 0,
    "alignment_non_positive_duration_count": 0,
    "alignment_tail_error_ms": -139.3877551020396,
    "alignment_abs_tail_error_ms": 139.3877551020396,
    "receiver_timed_out": false,
    "client_ttft_recv_ms": 126.88458303455263,
    "client_ttfb_msg_ms": 126.86095805838704,
    "client_total_audio_ms": 1328.3135000383481,
    "client_chars_per_s": 120.45349233850355,
    "run": 1,
    "run_id": "len-160-case-math_02-run-1-36eb94c1",
    "case": "math_02",
    "server_session": "1f5467ff",
    "server_ttft_audio_out_ms": 124.379,
    "server_ttft_send_ms": 126.193,
    "server_gap_buffer_to_synth_ms": 11.151,
    "server_gap_synth_to_first_chunk_ms": null,
    "server_gap_synth_to_backend_done_ms": 38.052,
    "server_gap_first_chunk_to_audio_out_ms": null,
    "server_gap_backend_done_to_audio_out_ms": 75.176,
    "server_gap_aligner_ms": 74.79,
    "server_gap_aligner_done_to_audio_out_ms": 0.039,
    "server_gap_math_normalize_ms": 0.014,
    "server_gap_audio_out_to_send_ms": 1.814,
    "server_model_compute_ms": 38.052,
    "server_post_model_to_audio_out_ms": 75.176,
    "client_minus_server_send_ms": NaN
  },
  {
    "chars": 160,
    "audio_chunks": 540,
    "audio_bytes": 1426432,
    "alignment_total_reported_chars": 238,
    "alignment_stream_chars": 238,
    "alignment_unique_indices": 90,
    "alignment_matched_chars": 106,
    "alignment_skipped_chars": 132,
    "alignment_missing_chars": 54,
    "alignment_coverage": 0.6625,
    "alignment_non_monotonic_count": 0,
    "alignment_non_positive_duration_count": 0,
    "alignment_tail_error_ms": -257.46031746031804,
    "alignment_abs_tail_error_ms": 257.46031746031804,
    "receiver_timed_out": false,
    "client_ttft_recv_ms": 137.6403330359608,
    "client_ttfb_msg_ms": 137.6165000256151,
    "client_total_audio_ms": 1778.3932080492377,
    "client_chars_per_s": 89.96885462439876,
    "run": 1,
    "run_id": "len-160-case-math_03-run-1-e19c3d61",
    "case": "math_03",
    "server_session": "8b9dd1fe",
    "server_ttft_audio_out_ms": 135.288,
    "server_ttft_send_ms": 137.017,
    "server_gap_buffer_to_synth_ms": 11.088,
    "server_gap_synth_to_first_chunk_ms": null,
    "server_gap_synth_to_backend_done_ms": 45.571,
    "server_gap_first_chunk_to_audio_out_ms": null,
    "server_gap_backend_done_to_audio_out_ms": 78.63,
    "server_gap_aligner_ms": 78.068,
    "server_gap_aligner_done_to_audio_out_ms": 0.042,
    "server_gap_math_normalize_ms": 0.013,
    "server_gap_audio_out_to_send_ms": 1.728,
    "server_model_compute_ms": 45.571,
    "server_post_model_to_audio_out_ms": 78.63,
    "client_minus_server_send_ms": NaN
  },
  {
    "chars": 160,
    "audio_chunks": 501,
    "audio_bytes": 1321984,
    "alignment_total_reported_chars": 227,
    "alignment_stream_chars": 227,
    "alignment_unique_indices": 77,
    "alignment_matched_chars": 109,
    "alignment_skipped_chars": 118,
    "alignment_missing_chars": 51,
    "alignment_coverage": 0.68125,
    "alignment_non_monotonic_count": 0,
    "alignment_non_positive_duration_count": 0,
    "alignment_tail_error_ms": -191.97278911564717,
    "alignment_abs_tail_error_ms": 191.97278911564717,
    "receiver_timed_out": false,
    "client_ttft_recv_ms": 143.42616708017886,
    "client_ttfb_msg_ms": 143.4022500179708,
    "client_total_audio_ms": 1634.1051670024171,
    "client_chars_per_s": 97.91291480553977,
    "run": 1,
    "run_id": "len-160-case-math_04-run-1-eb676d38",
    "case": "math_04",
    "server_session": "ef5950eb",
    "server_ttft_audio_out_ms": 140.983,
    "server_ttft_send_ms": 142.826,
    "server_gap_buffer_to_synth_ms": 11.146,
    "server_gap_synth_to_first_chunk_ms": null,
    "server_gap_synth_to_backend_done_ms": 50.789,
    "server_gap_first_chunk_to_audio_out_ms": null,
    "server_gap_backend_done_to_audio_out_ms": 79.048,
    "server_gap_aligner_ms": 78.313,
    "server_gap_aligner_done_to_audio_out_ms": 0.041,
    "server_gap_math_normalize_ms": 0.013,
    "server_gap_audio_out_to_send_ms": 1.842,
    "server_model_compute_ms": 50.789,
    "server_post_model_to_audio_out_ms": 79.048,
    "client_minus_server_send_ms": NaN
  },
  {
    "chars": 160,
    "audio_chunks": 604,
    "audio_bytes": 1597440,
    "alignment_total_reported_chars": 289,
    "alignment_stream_chars": 289,
    "alignment_unique_indices": 103,
    "alignment_matched_chars": 115,
    "alignment_skipped_chars": 174,
    "alignment_missing_chars": 45,
    "alignment_coverage": 0.71875,
    "alignment_non_monotonic_count": 0,
    "alignment_non_positive_duration_count": 0,
    "alignment_tail_error_ms": -171.83673469387577,
    "alignment_abs_tail_error_ms": 171.83673469387577,
    "receiver_timed_out": false,
    "client_ttft_recv_ms": 148.40708300471306,
    "client_ttfb_msg_ms": 148.38329202029854,
    "client_total_audio_ms": 1964.4966670311987,
    "client_chars_per_s": 81.44579865426618,
    "run": 1,
    "run_id": "len-160-case-math_05-run-1-bd103a99",
    "case": "math_05",
    "server_session": "5f3bdbd8",
    "server_ttft_audio_out_ms": 145.179,
    "server_ttft_send_ms": 147.359,
    "server_gap_buffer_to_synth_ms": 10.733,
    "server_gap_synth_to_first_chunk_ms": null,
    "server_gap_synth_to_backend_done_ms": 52.806,
    "server_gap_first_chunk_to_audio_out_ms": null,
    "server_gap_backend_done_to_audio_out_ms": 81.64,
    "server_gap_aligner_ms": 81.07,
    "server_gap_aligner_done_to_audio_out_ms": 0.041,
    "server_gap_math_normalize_ms": 0.014,
    "server_gap_audio_out_to_send_ms": 2.18,
    "server_model_compute_ms": 52.806,
    "server_post_model_to_audio_out_ms": 81.64,
    "client_minus_server_send_ms": NaN
  },
  {
    "chars": 160,
    "audio_chunks": 793,
    "audio_bytes": 2096128,
    "alignment_total_reported_chars": 323,
    "alignment_stream_chars": 323,
    "alignment_unique_indices": 91,
    "alignment_matched_chars": 91,
    "alignment_skipped_chars": 232,
    "alignment_missing_chars": 69,
    "alignment_coverage": 0.56875,
    "alignment_non_monotonic_count": 0,
    "alignment_non_positive_duration_count": 0,
    "alignment_tail_error_ms": -164.53514739229286,
    "alignment_abs_tail_error_ms": 164.53514739229286,
    "receiver_timed_out": false,
    "client_ttft_recv_ms": 131.1126248911023,
    "client_ttfb_msg_ms": 131.0882499674335,
    "client_total_audio_ms": 2586.824999889359,
    "client_chars_per_s": 61.85188406902027,
    "run": 1,
    "run_id": "len-160-case-math_06-run-1-16cfdae8",
    "case": "math_06",
    "server_session": "26de3519",
    "server_ttft_audio_out_ms": 128.315,
    "server_ttft_send_ms": 130.391,
    "server_gap_buffer_to_synth_ms": 11.372,
    "server_gap_synth_to_first_chunk_ms": null,
    "server_gap_synth_to_backend_done_ms": 40.317,
    "server_gap_first_chunk_to_audio_out_ms": null,
    "server_gap_backend_done_to_audio_out_ms": 76.627,
    "server_gap_aligner_ms": 76.19,
    "server_gap_aligner_done_to_audio_out_ms": 0.047,
    "server_gap_math_normalize_ms": 0.014,
    "server_gap_audio_out_to_send_ms": 2.076,
    "server_model_compute_ms": 40.317,
    "server_post_model_to_audio_out_ms": 76.627,
    "client_minus_server_send_ms": NaN
  },
  {
    "chars": 160,
    "audio_chunks": 313,
    "audio_bytes": 823296,
    "alignment_total_reported_chars": 132,
    "alignment_stream_chars": 132,
    "alignment_unique_indices": 108,
    "alignment_matched_chars": 118,
    "alignment_skipped_chars": 14,
    "alignment_missing_chars": 42,
    "alignment_coverage": 0.7375,
    "alignment_non_monotonic_count": 0,
    "alignment_non_positive_duration_count": 0,
    "alignment_tail_error_ms": -330.79365079364834,
    "alignment_abs_tail_error_ms": 330.79365079364834,
    "receiver_timed_out": false,
    "client_ttft_recv_ms": 141.1199999274686,
    "client_ttfb_msg_ms": 141.09695795923471,
    "client_total_audio_ms": 954.6644579386339,
    "client_chars_per_s": 167.59815312018753,
    "run": 1,
    "run_id": "len-160-case-math_07-run-1-294fb625",
    "case": "math_07",
    "server_session": "77a53a53",
    "server_ttft_audio_out_ms": 138.948,
    "server_ttft_send_ms": 140.498,
    "server_gap_buffer_to_synth_ms": 11.456,
    "server_gap_synth_to_first_chunk_ms": null,
    "server_gap_synth_to_backend_done_ms": 46.343,
    "server_gap_first_chunk_to_audio_out_ms": null,
    "server_gap_backend_done_to_audio_out_ms": 81.15,
    "server_gap_aligner_ms": 80.651,
    "server_gap_aligner_done_to_audio_out_ms": 0.04,
    "server_gap_math_normalize_ms": 0.013,
    "server_gap_audio_out_to_send_ms": 1.55,
    "server_model_compute_ms": 46.343,
    "server_post_model_to_audio_out_ms": 81.15,
    "client_minus_server_send_ms": NaN
  },
  {
    "chars": 160,
    "audio_chunks": 550,
    "audio_bytes": 1452032,
    "alignment_total_reported_chars": 241,
    "alignment_stream_chars": 241,
    "alignment_unique_indices": 129,
    "alignment_matched_chars": 151,
    "alignment_skipped_chars": 90,
    "alignment_missing_chars": 9,
    "alignment_coverage": 0.94375,
    "alignment_non_monotonic_count": 0,
    "alignment_non_positive_duration_count": 0,
    "alignment_tail_error_ms": -276.68934240362796,
    "alignment_abs_tail_error_ms": 276.68934240362796,
    "receiver_timed_out": false,
    "client_ttft_recv_ms": 135.8365420019254,
    "client_ttfb_msg_ms": 135.80912502948195,
    "client_total_audio_ms": 1854.3547079898417,
    "client_chars_per_s": 86.28338435500469,
    "run": 1,
    "run_id": "len-160-case-units_01-run-1-1672dd72",
    "case": "units_01",
    "server_session": "e445f3a2",
    "server_ttft_audio_out_ms": 132.713,
    "server_ttft_send_ms": 134.786,
    "server_gap_buffer_to_synth_ms": 10.741,
    "server_gap_synth_to_first_chunk_ms": null,
    "server_gap_synth_to_backend_done_ms": 40.754,
    "server_gap_first_chunk_to_audio_out_ms": null,
    "server_gap_backend_done_to_audio_out_ms": 81.219,
    "server_gap_aligner_ms": 79.868,
    "server_gap_aligner_done_to_audio_out_ms": 0.041,
    "server_gap_math_normalize_ms": 0.014,
    "server_gap_audio_out_to_send_ms": 2.073,
    "server_model_compute_ms": 40.754,
    "server_post_model_to_audio_out_ms": 81.219,
    "client_minus_server_send_ms": NaN
  },
  {
    "chars": 160,
    "audio_chunks": 503,
    "audio_bytes": 1330176,
    "alignment_total_reported_chars": 166,
    "alignment_stream_chars": 166,
    "alignment_unique_indices": 138,
    "alignment_matched_chars": 158,
    "alignment_skipped_chars": 8,
    "alignment_missing_chars": 2,
    "alignment_coverage": 0.9875,
    "alignment_non_monotonic_count": 0,
    "alignment_non_positive_duration_count": 0,
    "alignment_tail_error_ms": -173.4920634920636,
    "alignment_abs_tail_error_ms": 173.4920634920636,
    "receiver_timed_out": false,
    "client_ttft_recv_ms": 131.40770804602653,
    "client_ttfb_msg_ms": 131.38266699388623,
    "client_total_audio_ms": 1660.3424169588834,
    "client_chars_per_s": 96.36566431462929,
    "run": 1,
    "run_id": "len-160-case-units_02-run-1-3918d2e6",
    "case": "units_02",
    "server_session": "d930e577",
    "server_ttft_audio_out_ms": 128.967,
    "server_ttft_send_ms": 130.706,
    "server_gap_buffer_to_synth_ms": 11.31,
    "server_gap_synth_to_first_chunk_ms": null,
    "server_gap_synth_to_backend_done_ms": 39.072,
    "server_gap_first_chunk_to_audio_out_ms": null,
    "server_gap_backend_done_to_audio_out_ms": 78.585,
    "server_gap_aligner_ms": 78.071,
    "server_gap_aligner_done_to_audio_out_ms": 0.039,
    "server_gap_math_normalize_ms": 0.014,
    "server_gap_audio_out_to_send_ms": 1.74,
    "server_model_compute_ms": 39.072,
    "server_post_model_to_audio_out_ms": 78.585,
    "client_minus_server_send_ms": NaN
  },
  {
    "chars": 160,
    "audio_chunks": 557,
    "audio_bytes": 1469440,
    "alignment_total_reported_chars": 211,
    "alignment_stream_chars": 211,
    "alignment_unique_indices": 134,
    "alignment_matched_chars": 160,
    "alignment_skipped_chars": 51,
    "alignment_missing_chars": 0,
    "alignment_coverage": 1.0,
    "alignment_non_monotonic_count": 0,
    "alignment_non_positive_duration_count": 0,
    "alignment_tail_error_ms": -247.70975056689713,
    "alignment_abs_tail_error_ms": 247.70975056689713,
    "receiver_timed_out": false,
    "client_ttft_recv_ms": 156.10716596711427,
    "client_ttfb_msg_ms": 156.08533297199756,
    "client_total_audio_ms": 1808.5036249831319,
    "client_chars_per_s": 88.47093132118678,
    "run": 1,
    "run_id": "len-160-case-units_03-run-1-6bcfd44c",
    "case": "units_03",
    "server_session": "f17bcb82",
    "server_ttft_audio_out_ms": 153.159,
    "server_ttft_send_ms": 155.152,
    "server_gap_buffer_to_synth_ms": 10.848,
    "server_gap_synth_to_first_chunk_ms": null,
    "server_gap_synth_to_backend_done_ms": 58.498,
    "server_gap_first_chunk_to_audio_out_ms": null,
    "server_gap_backend_done_to_audio_out_ms": 83.813,
    "server_gap_aligner_ms": 83.224,
    "server_gap_aligner_done_to_audio_out_ms": 0.038,
    "server_gap_math_normalize_ms": 0.014,
    "server_gap_audio_out_to_send_ms": 1.992,
    "server_model_compute_ms": 58.498,
    "server_post_model_to_audio_out_ms": 83.813,
    "client_minus_server_send_ms": NaN
  },
  {
    "chars": 160,
    "audio_chunks": 655,
    "audio_bytes": 1730560,
    "alignment_total_reported_chars": 173,
    "alignment_stream_chars": 173,
    "alignment_unique_indices": 135,
    "alignment_matched_chars": 157,
    "alignment_skipped_chars": 16,
    "alignment_missing_chars": 3,
    "alignment_coverage": 0.98125,
    "alignment_non_monotonic_count": 0,
    "alignment_non_positive_duration_count": 0,
    "alignment_tail_error_ms": -214.01360544217823,
    "alignment_abs_tail_error_ms": 214.01360544217823,
    "receiver_timed_out": false,
    "client_ttft_recv_ms": 140.26474999263883,
    "client_ttfb_msg_ms": 140.2409999864176,
    "client_total_audio_ms": 3083.6615840671584,
    "client_chars_per_s": 51.88636808484345,
    "run": 1,
    "run_id": "len-160-case-money_01-run-1-4d941038",
    "case": "money_01",
    "server_session": "95994119",
    "server_ttft_audio_out_ms": 137.924,
    "server_ttft_send_ms": 139.641,
    "server_gap_buffer_to_synth_ms": 11.306,
    "server_gap_synth_to_first_chunk_ms": null,
    "server_gap_synth_to_backend_done_ms": 46.161,
    "server_gap_first_chunk_to_audio_out_ms": null,
    "server_gap_backend_done_to_audio_out_ms": 80.456,
    "server_gap_aligner_ms": 79.366,
    "server_gap_aligner_done_to_audio_out_ms": 0.046,
    "server_gap_math_normalize_ms": 0.014,
    "server_gap_audio_out_to_send_ms": 1.718,
    "server_model_compute_ms": 46.161,
    "server_post_model_to_audio_out_ms": 80.456,
    "client_minus_server_send_ms": NaN
  },
  {
    "chars": 160,
    "audio_chunks": 515,
    "audio_bytes": 1361920,
    "alignment_total_reported_chars": 196,
    "alignment_stream_chars": 196,
    "alignment_unique_indices": 148,
    "alignment_matched_chars": 154,
    "alignment_skipped_chars": 42,
    "alignment_missing_chars": 6,
    "alignment_coverage": 0.9625,
    "alignment_non_monotonic_count": 0,
    "alignment_non_positive_duration_count": 0,
    "alignment_tail_error_ms": 0.5283446712019213,
    "alignment_abs_tail_error_ms": 0.5283446712019213,
    "receiver_timed_out": false,
    "client_ttft_recv_ms": 142.5735839875415,
    "client_ttfb_msg_ms": 142.55362504627556,
    "client_total_audio_ms": 2047.8270839666948,
    "client_chars_per_s": 78.1315967801714,
    "run": 1,
    "run_id": "len-160-case-money_02-run-1-edba9323",
    "case": "money_02",
    "server_session": "9d8e5134",
    "server_ttft_audio_out_ms": 139.813,
    "server_ttft_send_ms": 141.761,
    "server_gap_buffer_to_synth_ms": 11.416,
    "server_gap_synth_to_first_chunk_ms": null,
    "server_gap_synth_to_backend_done_ms": 45.678,
    "server_gap_first_chunk_to_audio_out_ms": null,
    "server_gap_backend_done_to_audio_out_ms": 82.719,
    "server_gap_aligner_ms": 82.126,
    "server_gap_aligner_done_to_audio_out_ms": 0.05,
    "server_gap_math_normalize_ms": 0.019,
    "server_gap_audio_out_to_send_ms": 1.948,
    "server_model_compute_ms": 45.678,
    "server_post_model_to_audio_out_ms": 82.719,
    "client_minus_server_send_ms": NaN
  },
  {
    "chars": 160,
    "audio_chunks": 533,
    "audio_bytes": 1408000,
    "alignment_total_reported_chars": 158,
    "alignment_stream_chars": 158,
    "alignment_unique_indices": 139,
    "alignment_matched_chars": 158,
    "alignment_skipped_chars": 0,
    "alignment_missing_chars": 2,
    "alignment_coverage": 0.9875,
    "alignment_non_monotonic_count": 0,
    "alignment_non_positive_duration_count": 0,
    "alignment_tail_error_ms": -2459.0702947845803,
    "alignment_abs_tail_error_ms": 2459.0702947845803,
    "receiver_timed_out": false,
    "client_ttft_recv_ms": 129.63187496643513,
    "client_ttfb_msg_ms": 129.61004092358053,
    "client_total_audio_ms": 1967.9484999505803,
    "client_chars_per_s": 81.30294060236737,
    "run": 1,
    "run_id": "len-160-case-dates_01-run-1-14c70f74",
    "case": "dates_01",
    "server_session": "fabafa0c",
    "server_ttft_audio_out_ms": 127.117,
    "server_ttft_send_ms": 128.793,
    "server_gap_buffer_to_synth_ms": 10.903,
    "server_gap_synth_to_first_chunk_ms": null,
    "server_gap_synth_to_backend_done_ms": 39.096,
    "server_gap_first_chunk_to_audio_out_ms": null,
    "server_gap_backend_done_to_audio_out_ms": 77.118,
    "server_gap_aligner_ms": 76.724,
    "server_gap_aligner_done_to_audio_out_ms": 0.051,
    "server_gap_math_normalize_ms": 0.015,
    "server_gap_audio_out_to_send_ms": 1.676,
    "server_model_compute_ms": 39.096,
    "server_post_model_to_audio_out_ms": 77.118,
    "client_minus_server_send_ms": NaN
  },
  {
    "chars": 160,
    "audio_chunks": 518,
    "audio_bytes": 1368064,
    "alignment_total_reported_chars": 160,
    "alignment_stream_chars": 160,
    "alignment_unique_indices": 150,
    "alignment_matched_chars": 160,
    "alignment_skipped_chars": 0,
    "alignment_missing_chars": 0,
    "alignment_coverage": 1.0,
    "alignment_non_monotonic_count": 0,
    "alignment_non_positive_duration_count": 0,
    "alignment_tail_error_ms": -229.5011337868491,
    "alignment_abs_tail_error_ms": 229.5011337868491,
    "receiver_timed_out": false,
    "client_ttft_recv_ms": 140.4069159179926,
    "client_ttfb_msg_ms": 140.38404100574553,
    "client_total_audio_ms": 2034.2363329837099,
    "client_chars_per_s": 78.65359467123493,
    "run": 1,
    "run_id": "len-160-case-dates_02-run-1-f29bf0dd",
    "case": "dates_02",
    "server_session": "232c49f0",
    "server_ttft_audio_out_ms": 137.607,
    "server_ttft_send_ms": 139.588,
    "server_gap_buffer_to_synth_ms": 11.57,
    "server_gap_synth_to_first_chunk_ms": null,
    "server_gap_synth_to_backend_done_ms": 42.165,
    "server_gap_first_chunk_to_audio_out_ms": null,
    "server_gap_backend_done_to_audio_out_ms": 83.871,
    "server_gap_aligner_ms": 83.297,
    "server_gap_aligner_done_to_audio_out_ms": 0.045,
    "server_gap_math_normalize_ms": 0.015,
    "server_gap_audio_out_to_send_ms": 1.981,
    "server_model_compute_ms": 42.165,
    "server_post_model_to_audio_out_ms": 83.871,
    "client_minus_server_send_ms": NaN
  },
  {
    "chars": 160,
    "audio_chunks": 396,
    "audio_bytes": 1046528,
    "alignment_total_reported_chars": 159,
    "alignment_stream_chars": 159,
    "alignment_unique_indices": 159,
    "alignment_matched_chars": 159,
    "alignment_skipped_chars": 0,
    "alignment_missing_chars": 1,
    "alignment_coverage": 0.99375,
    "alignment_non_monotonic_count": 0,
    "alignment_non_positive_duration_count": 0,
    "alignment_tail_error_ms": 0.5918367346948799,
    "alignment_abs_tail_error_ms": 0.5918367346948799,
    "receiver_timed_out": false,
    "client_ttft_recv_ms": 124.35745901893824,
    "client_ttfb_msg_ms": 124.33312507346272,
    "client_total_audio_ms": 1421.8189590610564,
    "client_chars_per_s": 112.53190779342337,
    "run": 1,
    "run_id": "len-160-case-abbr_01-run-1-1dd58959",
    "case": "abbr_01",
    "server_session": "40e920fe",
    "server_ttft_audio_out_ms": 121.894,
    "server_ttft_send_ms": 123.418,
    "server_gap_buffer_to_synth_ms": 0.053,
    "server_gap_synth_to_first_chunk_ms": null,
    "server_gap_synth_to_backend_done_ms": 37.715,
    "server_gap_first_chunk_to_audio_out_ms": null,
    "server_gap_backend_done_to_audio_out_ms": 84.126,
    "server_gap_aligner_ms": 83.657,
    "server_gap_aligner_done_to_audio_out_ms": 0.041,
    "server_gap_math_normalize_ms": 0.011,
    "server_gap_audio_out_to_send_ms": 1.524,
    "server_model_compute_ms": 37.715,
    "server_post_model_to_audio_out_ms": 84.126,
    "client_minus_server_send_ms": NaN
  },
  {
    "chars": 160,
    "audio_chunks": 616,
    "audio_bytes": 1629184,
    "alignment_total_reported_chars": 200,
    "alignment_stream_chars": 200,
    "alignment_unique_indices": 137,
    "alignment_matched_chars": 156,
    "alignment_skipped_chars": 44,
    "alignment_missing_chars": 4,
    "alignment_coverage": 0.975,
    "alignment_non_monotonic_count": 0,
    "alignment_non_positive_duration_count": 0,
    "alignment_tail_error_ms": 0.4036281179141952,
    "alignment_abs_tail_error_ms": 0.4036281179141952,
    "receiver_timed_out": false,
    "client_ttft_recv_ms": 319.18341701384634,
    "client_ttfb_msg_ms": 319.1547089954838,
    "client_total_audio_ms": 3211.5872090216726,
    "client_chars_per_s": 49.819603076803844,
    "run": 1,
    "run_id": "len-160-case-abbr_02-run-1-099acf21",
    "case": "abbr_02",
    "server_session": "0e98f525",
    "server_ttft_audio_out_ms": 315.884,
    "server_ttft_send_ms": 318.272,
    "server_gap_buffer_to_synth_ms": 10.839,
    "server_gap_synth_to_first_chunk_ms": null,
    "server_gap_synth_to_backend_done_ms": 90.996,
    "server_gap_first_chunk_to_audio_out_ms": null,
    "server_gap_backend_done_to_audio_out_ms": 214.049,
    "server_gap_aligner_ms": 211.893,
    "server_gap_aligner_done_to_audio_out_ms": 0.053,
    "server_gap_math_normalize_ms": 0.029,
    "server_gap_audio_out_to_send_ms": 2.388,
    "server_model_compute_ms": 90.996,
    "server_post_model_to_audio_out_ms": 214.049,
    "client_minus_server_send_ms": NaN
  },
  {
    "chars": 160,
    "audio_chunks": 398,
    "audio_bytes": 1051648,
    "alignment_total_reported_chars": 173,
    "alignment_stream_chars": 173,
    "alignment_unique_indices": 153,
    "alignment_matched_chars": 157,
    "alignment_skipped_chars": 16,
    "alignment_missing_chars": 3,
    "alignment_coverage": 0.98125,
    "alignment_non_monotonic_count": 0,
    "alignment_non_positive_duration_count": 0,
    "alignment_tail_error_ms": 0.8117913832211343,
    "alignment_abs_tail_error_ms": 0.8117913832211343,
    "receiver_timed_out": false,
    "client_ttft_recv_ms": 135.23750007152557,
    "client_ttfb_msg_ms": 135.2045841049403,
    "client_total_audio_ms": 1656.9479590980336,
    "client_chars_per_s": 96.5630810077443,
    "run": 1,
    "run_id": "len-160-case-mixed_01-run-1-bb3d7f25",
    "case": "mixed_01",
    "server_session": "123882ea",
    "server_ttft_audio_out_ms": 132.486,
    "server_ttft_send_ms": 134.106,
    "server_gap_buffer_to_synth_ms": 10.765,
    "server_gap_synth_to_first_chunk_ms": null,
    "server_gap_synth_to_backend_done_ms": 42.585,
    "server_gap_first_chunk_to_audio_out_ms": null,
    "server_gap_backend_done_to_audio_out_ms": 79.136,
    "server_gap_aligner_ms": 78.636,
    "server_gap_aligner_done_to_audio_out_ms": 0.049,
    "server_gap_math_normalize_ms": 0.023,
    "server_gap_audio_out_to_send_ms": 1.62,
    "server_model_compute_ms": 42.585,
    "server_post_model_to_audio_out_ms": 79.136,
    "client_minus_server_send_ms": NaN
  },
  {
    "chars": 160,
    "audio_chunks": 354,
    "audio_bytes": 935936,
    "alignment_total_reported_chars": 159,
    "alignment_stream_chars": 159,
    "alignment_unique_indices": 159,
    "alignment_matched_chars": 159,
    "alignment_skipped_chars": 0,
    "alignment_missing_chars": 1,
    "alignment_coverage": 0.99375,
    "alignment_non_monotonic_count": 0,
    "alignment_non_positive_duration_count": 0,
    "alignment_tail_error_ms": -236.62131519274408,
    "alignment_abs_tail_error_ms": 236.62131519274408,
    "receiver_timed_out": false,
    "client_ttft_recv_ms": 243.31008293665946,
    "client_ttfb_msg_ms": 243.28083300497383,
    "client_total_audio_ms": 1551.7975420225412,
    "client_chars_per_s": 103.1062336852676,
    "run": 1,
    "run_id": "len-160-case-mixed_02-run-1-c321a7e9",
    "case": "mixed_02",
    "server_session": "574c3adb",
    "server_ttft_audio_out_ms": 239.365,
    "server_ttft_send_ms": 241.865,
    "server_gap_buffer_to_synth_ms": 10.833,
    "server_gap_synth_to_first_chunk_ms": null,
    "server_gap_synth_to_backend_done_ms": 63.578,
    "server_gap_first_chunk_to_audio_out_ms": null,
    "server_gap_backend_done_to_audio_out_ms": 164.954,
    "server_gap_aligner_ms": 164.221,
    "server_gap_aligner_done_to_audio_out_ms": 0.061,
    "server_gap_math_normalize_ms": 0.016,
    "server_gap_audio_out_to_send_ms": 2.5,
    "server_model_compute_ms": 63.578,
    "server_post_model_to_audio_out_ms": 164.954,
    "client_minus_server_send_ms": NaN
  },
  {
    "chars": 160,
    "audio_chunks": 450,
    "audio_bytes": 1187840,
    "alignment_total_reported_chars": 160,
    "alignment_stream_chars": 160,
    "alignment_unique_indices": 154,
    "alignment_matched_chars": 160,
    "alignment_skipped_chars": 0,
    "alignment_missing_chars": 0,
    "alignment_coverage": 1.0,
    "alignment_non_monotonic_count": 0,
    "alignment_non_positive_duration_count": 0,
    "alignment_tail_error_ms": -141.06575963718933,
    "alignment_abs_tail_error_ms": 141.06575963718933,
    "receiver_timed_out": false,
    "client_ttft_recv_ms": 188.7470840010792,
    "client_ttfb_msg_ms": 188.70741699356586,
    "client_total_audio_ms": 1707.6323749497533,
    "client_chars_per_s": 93.69698205956534,
    "run": 1,
    "run_id": "len-160-case-mixed_03-run-1-acc59ff2",
    "case": "mixed_03",
    "server_session": "e6985316",
    "server_ttft_audio_out_ms": 185.833,
    "server_ttft_send_ms": 187.556,
    "server_gap_buffer_to_synth_ms": 10.782,
    "server_gap_synth_to_first_chunk_ms": null,
    "server_gap_synth_to_backend_done_ms": 68.981,
    "server_gap_first_chunk_to_audio_out_ms": null,
    "server_gap_backend_done_to_audio_out_ms": 106.071,
    "server_gap_aligner_ms": 105.38,
    "server_gap_aligner_done_to_audio_out_ms": 0.045,
    "server_gap_math_normalize_ms": 0.017,
    "server_gap_audio_out_to_send_ms": 1.722,
    "server_model_compute_ms": 68.981,
    "server_post_model_to_audio_out_ms": 106.071,
    "client_minus_server_send_ms": NaN
  },
  {
    "chars": 160,
    "audio_chunks": 347,
    "audio_bytes": 916480,
    "alignment_total_reported_chars": 160,
    "alignment_stream_chars": 160,
    "alignment_unique_indices": 160,
    "alignment_matched_chars": 160,
    "alignment_skipped_chars": 0,
    "alignment_missing_chars": 0,
    "alignment_coverage": 1.0,
    "alignment_non_monotonic_count": 0,
    "alignment_non_positive_duration_count": 0,
    "alignment_tail_error_ms": -253.15192743764055,
    "alignment_abs_tail_error_ms": 253.15192743764055,
    "receiver_timed_out": false,
    "client_ttft_recv_ms": 158.53170794434845,
    "client_ttfb_msg_ms": 158.50925003178418,
    "client_total_audio_ms": 1313.2080000359565,
    "client_chars_per_s": 121.83903844297255,
    "run": 1,
    "run_id": "len-160-case-mixed_04-run-1-eaf1e731",
    "case": "mixed_04",
    "server_session": "9943ac54",
    "server_ttft_audio_out_ms": 155.284,
    "server_ttft_send_ms": 157.329,
    "server_gap_buffer_to_synth_ms": 10.633,
    "server_gap_synth_to_first_chunk_ms": null,
    "server_gap_synth_to_backend_done_ms": 58.909,
    "server_gap_first_chunk_to_audio_out_ms": null,
    "server_gap_backend_done_to_audio_out_ms": 85.742,
    "server_gap_aligner_ms": 84.808,
    "server_gap_aligner_done_to_audio_out_ms": 0.044,
    "server_gap_math_normalize_ms": 0.015,
    "server_gap_audio_out_to_send_ms": 2.045,
    "server_model_compute_ms": 58.909,
    "server_post_model_to_audio_out_ms": 85.742,
    "client_minus_server_send_ms": NaN
  }
]